GFS/GeneticFuzzySystem.py
GFS/__init__.py
GFS/example.py
GFS/FIS/Antecedent.py
GFS/FIS/Consequent.py
GFS/FIS/DecisionSystem.py
GFS/FIS/DecisionSystemSimulation.py
GFS/FIS/FuzzyVariable.py
GFS/FIS/Rule.py
GFS/FIS/RuleLib.py
GFS/FIS/Term.py
GFS/FIS/__init__.py
GFS/Tools/GFTBoard.py
GFS/Tools/__init__.py
gfs-1.0.1.dist-info/LICENSE.txt
gfs-1.0.1.dist-info/METADATA
gfs-1.0.1.dist-info/WHEEL
gfs-1.0.1.dist-info/top_level.txt
gfs-1.0.1.dist-info/RECORD
